delumps-0.1.10.dist-info/METADATA
delumps-0.1.10.dist-info/WHEEL
delumps/__init__.py
delumps/__init__.pyi
delumps/delumps.abi3.so
delumps/py.typed
delumps-0.1.10.dist-info/RECORD
