Metadata-Version: 2.4
Name: delumps
Version: 0.1.10
Classifier: Development Status :: 3 - Alpha
Classifier: Intended Audience :: Developers
Classifier: Operating System :: OS Independent
Classifier: Programming Language :: Python
Classifier: Programming Language :: Python :: 3.10
Classifier: Programming Language :: Python :: 3.11
Classifier: Programming Language :: Python :: 3 :: Only
Requires-Dist: numpy>=1.23.0 ; extra == 'test'
Requires-Dist: pytest>=8.0.0,<9.0.0 ; extra == 'test'
Provides-Extra: test
Summary: Rust extension module for Scone semantic similarity library
Keywords: HPO,similarity
Author: Daniel Danis <daniel.gordon.danis@protonmail.com>
Author-email: Daniel Danis <daniel.gordon.danis@protonmail.com>
License: MIT
Requires-Python: >=3.10
Project-URL: homepage, https://github.com/P2GX/delumps
Project-URL: documentation, https://github.com/P2GX/delumps
Project-URL: repository, https://github.com/P2GX/delumps
